LICENSE.TXT
README.md
setup.py
akris_desktop/__init__.py
akris_desktop/app.py
akris_desktop/broadcast_message_entry.py
akris_desktop/broadcast_tab.py
akris_desktop/broadcast_view.py
akris_desktop/chain.py
akris_desktop/console.py
akris_desktop/direct_message_entry.py
akris_desktop/direct_tab.py
akris_desktop/direct_view.py
akris_desktop/handle_set_listener.py
akris_desktop/main.py
akris_desktop/master.py
akris_desktop/message_entry.py
akris_desktop/message_stats_listener.py
akris_desktop/new_handle_listener.py
akris_desktop/new_ref_link_listener.py
akris_desktop/notifications.py
akris_desktop/page_monitor.py
akris_desktop/peers.py
akris_desktop/ref_link_tab.py
akris_desktop/ref_link_view.py
akris_desktop/text_utils.py
akris_desktop/timeline.py
akris_desktop/timeline_view.py
akris_desktop/version.py
akris_desktop.egg-info/PKG-INFO
akris_desktop.egg-info/SOURCES.txt
akris_desktop.egg-info/dependency_links.txt
akris_desktop.egg-info/entry_points.txt
akris_desktop.egg-info/requires.txt
akris_desktop.egg-info/top_level.txt
akris_desktop/console_renderers/__init__.py
akris_desktop/console_renderers/at.py
akris_desktop/console_renderers/default.py
akris_desktop/console_renderers/error.py
akris_desktop/console_renderers/help.py
akris_desktop/console_renderers/knob.py
akris_desktop/console_renderers/search.py
akris_desktop/console_renderers/version_info.py
akris_desktop/console_renderers/wot.py
akris_desktop/emojis/__init__.py
akris_desktop/emojis/emojis.py
akris_desktop/emojis/db/__init__.py
akris_desktop/emojis/db/db.py
akris_desktop/emojis/db/generator.py
akris_desktop/emojis/db/utils.py
tests/test_at_command.py
tests/test_display_broadcast_text.py
tests/test_knob_command.py
tests/test_populate_peers.py
tests/test_timeline.py