Metadata-Version: 2.4
Name: akris-desktop
Version: 1.0.1
Summary: A gui client for akris
Home-page: http://v.alethepedia.com/akris_desktop
Author: Adam Thorsen
Author-email: awt@fastmail.fm
License: VPL
Keywords: p2p pest forum
Classifier: Development Status :: 3 - Alpha
Classifier: Intended Audience :: Developers
Classifier: Natural Language :: English
Classifier: Programming Language :: Python :: 3
Requires-Python: >=3.11
License-File: LICENSE.TXT
Requires-Dist: Pillow
Requires-Dist: akris
Provides-Extra: dev
Requires-Dist: black; extra == "dev"
Requires-Dist: pytest; extra == "dev"
Requires-Dist: pytest-mock; extra == "dev"
Requires-Dist: autopep8; extra == "dev"
Requires-Dist: pyinstaller; extra == "dev"
Requires-Dist: markdown2; extra == "dev"
Requires-Dist: staticx; extra == "dev"
Requires-Dist: pylint; extra == "dev"
Dynamic: author
Dynamic: author-email
Dynamic: classifier
Dynamic: description
Dynamic: description-content-type
Dynamic: home-page
Dynamic: keywords
Dynamic: license
Dynamic: license-file
Dynamic: provides-extra
Dynamic: requires-dist
Dynamic: requires-python
Dynamic: summary
